vcr/__init__.py
vcr/_handle_coroutine.py
vcr/cassette.py
vcr/config.py
vcr/errors.py
vcr/filters.py
vcr/matchers.py
vcr/migration.py
vcr/patch.py
vcr/record_mode.py
vcr/request.py
vcr/serialize.py
vcr/unittest.py
vcr/util.py
vcr/persisters/__init__.py
vcr/persisters/filesystem.py
vcr/serializers/__init__.py
vcr/serializers/compat.py
vcr/serializers/jsonserializer.py
vcr/serializers/yamlserializer.py
vcr/stubs/__init__.py
vcr/stubs/aiohttp_stubs.py
vcr/stubs/boto3_stubs.py
vcr/stubs/compat.py
vcr/stubs/httpcore_stubs.py
vcr/stubs/httplib2_stubs.py
vcr/stubs/requests_stubs.py
vcr/stubs/tornado_stubs.py
vcr/stubs/urllib3_stubs.py
vcrpy-8.1.0.dist-info/licenses/LICENSE.txt
vcrpy-8.1.0.dist-info/METADATA
vcrpy-8.1.0.dist-info/WHEEL
vcrpy-8.1.0.dist-info/top_level.txt
vcrpy-8.1.0.dist-info/RECORD
